{"encoded":true,"video":[{"videoId":"5a0juQ0aeGI","channelId":"UCxuYPUdTZHRZKVRZ1km1plw","title":"Bryan%20Adams%20%26amp%3B%20Luciano%20Pavarotti%20-%20%26%2339%3BO%20Sole%20Mio","channelTitle":"Bryan%20Adams","selector":"music","category":"Music","thumbnailId":"5a0juQ0aeGI","views":"40,276,172"},{"videoId":"2tSOTQPUQoU","channelId":"UCeh7F2L-aITDyr_1mKoB33Q","title":"Good-bye%20Twitter","channelTitle":"mileymandy","selector":"comedy","category":"Comedy","thumbnailId":"2tSOTQPUQoU","views":"19,141,232"},{"videoId":"pCq7eGKcs-w","channelId":"UCRrI7yZ5gjf-_lmcBehmHBg","title":"Best%20scene%20pursuit%20of%20happyness%2C%20Will%20Smith%20at%20his%20best","channelTitle":"mpscsela","selector":"film_and_animation","category":"Film & Animation","thumbnailId":"pCq7eGKcs-w","views":"3,872,009"},{"videoId":"94MfmvvPDOY","channelId":"UC8iCpAaJz8Ku2hqBXc25XeA","title":"Luv%20Kush%20Mahalon%20Ke%20Adhikaari%20FULL","channelTitle":"lola610","selector":"entertainment","category":"Entertainment","thumbnailId":"94MfmvvPDOY","views":"9,280,037"},{"videoId":"7DHookJwrYg","channelId":"UCaxR-D8FjZ-2otbU0_Y2grg","title":"Rawalpindi%20GHQ%20Attack","channelTitle":"DawnNews","selector":"news_and_politics","category":"News & Politics","thumbnailId":"7DHookJwrYg","views":"4,709,778"},{"videoId":"q-H2Lil8zu8","channelId":"UCJTDxy4LKtV1KwcX-QNpYTg","title":"MAGIC%20Waking%20Up%20Andreas","channelTitle":"PoC%20-%20Pictures%20of%20Cats%20org","selector":"pets_and_animals","category":"Pets & Animals","thumbnailId":"q-H2Lil8zu8","views":"4,724,240"},{"videoId":"oeNLMN_RqSI","channelId":"UC392cEYFWnhIP15B5ZYQkUQ","title":"Frogman%20Tim%20Cotterill%20Rocket%20II%20Trike","channelTitle":"merynoosh","selector":"sports","category":"Sports","thumbnailId":"oeNLMN_RqSI","views":"3,494,236"},{"videoId":"ng0avV3ivAo","channelId":"UCnSv1D4c_LlAhD_dLtvQFKQ","title":"Meet%20the%20Nintendo%20Game%20Boy%20Family%21","channelTitle":"Area%20DMG","selector":"gaming","category":"Gaming","thumbnailId":"ng0avV3ivAo","views":"1,454,604"}]}